outliers_filtering/__init__.py
outliers_filtering/utils.py
outliers_filtering-0.1.0.dist-info/LICENSE
outliers_filtering-0.1.0.dist-info/METADATA
outliers_filtering-0.1.0.dist-info/WHEEL
outliers_filtering-0.1.0.dist-info/top_level.txt
outliers_filtering-0.1.0.dist-info/RECORD
