Metadata-Version: 2.1
Name: outliers-filtering
Version: 0.1.0
Summary: outliers_filtering package for Python-Guide.org
Home-page: https://github.com/vincent-belz/outliers_filtering
Author: Vincent Belz
Author-email: vincent.belz@loft.com.br
License: Copyright (c) 2017, Kenneth Reitz        
License-File: LICENSE
Requires-Dist: pytest
Requires-Dist: pandas
Requires-Dist: numpy
Requires-Dist: seaborn
Requires-Dist: matplotlib
